MANIFEST.in
README.rst
setup.py
boxmath/__init__.py
boxmath/fractions27.py
boxmath/fractions_compat.py
boxmath/model.py
boxmath.egg-info/PKG-INFO
boxmath.egg-info/SOURCES.txt
boxmath.egg-info/dependency_links.txt
boxmath.egg-info/top_level.txt