Metadata-Version: 1.0
Name: boxmath
Version: 0.1.3
Summary: Simple image box arithmetic
Home-page: http://github.com/ericmoritz/boxmath
Author: Eric Moritz
Author-email: eric@themoritzfamily.com
License: BSD License
Platform: UNKNOWN
Classifier: Development Status :: 3 - Alpha
Classifier: Intended Audience :: Developers
Classifier: License :: OSI Approved :: MIT License
Classifier: Programming Language :: Python :: 2.6
Classifier: Programming Language :: Python :: 2.7
Classifier: Programming Language :: Python :: 3.2
Classifier: Programming Language :: Python :: 3.3
Classifier: Programming Language :: Python :: Implementation :: CPython
Classifier: Programming Language :: Python :: Implementation :: PyPy
Classifier: Programming Language :: Python :: Implementation :: Stackless
Classifier: Topic :: Multimedia :: Graphics
